{"openapi":"3.0.3","info":{"title":"goa微服务","version":"1.0"},"servers":[{"url":"http://localhost:8000/starter","description":"goa微服务"}],"paths":{"/api/actual_time/get_actual_time_data":{"get":{"tags":["ActualTime"],"summary":"接收数据库监听得到的数据","description":"接收数据库监听得到的数据","operationId":"ActualTime#GetActualTimeData","responses":{"200":{"description":"","content":{"application/json":{"schema":{"$ref":"#/components/schemas/GetActualTimeDataResponseBody"},"example":{"data":{"dataInfo":1035,"dataType":1035},"errcode":0,"errmsg":""}}}},"400":{"description":"","content":{"application/vnd.goa.error":{"schema":{"$ref":"#/components/schemas/Error"},"example":{"fault":true,"id":"123abc","message":"parameter 'p' must be an integer","name":"bad_request","temporary":false,"timeout":true}}}},"500":{"description":"","content":{"application/vnd.goa.error":{"schema":{"$ref":"#/components/schemas/Error"},"example":{"fault":false,"id":"123abc","message":"parameter 'p' must be an integer","name":"bad_request","temporary":true,"timeout":true}}}}}}},"/api/actual_time/receive_third_party_push_data":{"post":{"tags":["ActualTime"],"summary":"接收第三方推送数据","description":"接收第三方推送数据--大厅排队办事实时图基础数据","operationId":"ActualTime#ReceiveThirdPartyPushData","requestBody":{"required":true,"content":{"application/json":{"schema":{"$ref":"#/components/schemas/ReceiveThirdPartyPushDataRequestBody"},"example":{"count":21,"data":"","methodName":1}}}},"responses":{"200":{"description":"","content":{"application/json":{"schema":{"$ref":"#/components/schemas/ReceiveThirdPartyPushDataResponseBody"},"example":{"errcode":0,"errmsg":"","result":"getDataSuccess"}}}},"400":{"description":"","content":{"application/vnd.goa.error":{"schema":{"$ref":"#/components/schemas/Error"},"example":{"fault":true,"id":"123abc","message":"parameter 'p' must be an integer","name":"bad_request","temporary":true,"timeout":true}}}},"500":{"description":"","content":{"application/vnd.goa.error":{"schema":{"$ref":"#/components/schemas/Error"},"example":{"fault":false,"id":"123abc","message":"parameter 'p' must be an integer","name":"bad_request","temporary":true,"timeout":false}}}}}}},"/api/entity_hall/get_wait_line_overview":{"post":{"tags":["entity_hall"],"summary":"排号总览","description":"排号总览","operationId":"entity_hall#WaitLineOverview","requestBody":{"required":true,"content":{"application/json":{"schema":{"$ref":"#/components/schemas/WaitLineOverviewRequestBody"},"example":{"endDate":"2020-07-27","regionCode":"520100","startDate":"2019-07-27"}}}},"responses":{"200":{"description":"","content":{"application/json":{"schema":{"$ref":"#/components/schemas/WaitLineOverviewResponseBody"},"example":{"data":{"cumulativeDQ":89362,"todayDQ":1035},"errcode":0,"errmsg":""}}}},"400":{"description":"","content":{"application/vnd.goa.error":{"schema":{"$ref":"#/components/schemas/Error"},"example":{"fault":false,"id":"123abc","message":"parameter 'p' must be an integer","name":"bad_request","temporary":true,"timeout":true}}}},"500":{"description":"","content":{"application/vnd.goa.error":{"schema":{"$ref":"#/components/schemas/Error"},"example":{"fault":true,"id":"123abc","message":"parameter 'p' must be an integer","name":"bad_request","temporary":true,"timeout":false}}}}}}},"/api/import_file/crowd_runs_little":{"post":{"tags":["import_file"],"summary":"群众少跑腿","description":"群众少跑腿","operationId":"import_file#CrowdRunsLittle","requestBody":{"required":true,"content":{"application/json":{"schema":{"$ref":"#/components/schemas/WaitLineOverviewRequestBody"},"example":{"endDate":"2020-07-27","regionCode":"520100","startDate":"2019-07-27"}}}},"responses":{"200":{"description":"","content":{"application/json":{"schema":{"$ref":"#/components/schemas/CrowdRunsLittleResponseBody"},"example":{"data":{"mattersAccounted":[{"AfterAscension":120,"beforeAscension":120},{"AfterAscension":120,"beforeAscension":120}],"mattersAccountedProportion":0.8},"errcode":0,"errmsg":""}}}},"400":{"description":"","content":{"application/vnd.goa.error":{"schema":{"$ref":"#/components/schemas/Error"},"example":{"fault":true,"id":"123abc","message":"parameter 'p' must be an integer","name":"bad_request","temporary":true,"timeout":true}}}},"500":{"description":"","content":{"application/vnd.goa.error":{"schema":{"$ref":"#/components/schemas/Error"},"example":{"fault":false,"id":"123abc","message":"parameter 'p' must be an integer","name":"bad_request","temporary":true,"timeout":false}}}}}}},"/api/import_file/get_import_excel_file_info":{"get":{"tags":["import_file"],"summary":"获取插入excel数据统计信息","description":"获取插入excel数据统计信息","operationId":"import_file#GetImportExcelFileInfo","parameters":[{"name":"endYear","in":"query","description":"结束年份","allowEmptyValue":true,"required":true,"schema":{"type":"integer","description":"结束年份","example":2020,"format":"int64"},"example":2020},{"name":"area","in":"query","description":"区域代码","allowEmptyValue":true,"schema":{"type":"string","description":"区域代码","example":"520103"},"example":"520103"}],"responses":{"200":{"description":"","content":{"application/json":{"schema":{"$ref":"#/components/schemas/FourDoCountResp"},"example":{"immediateInfoCount":[{"count":8618130149726945015,"year":144328607719150468},{"count":8618130149726945015,"year":144328607719150468},{"count":8618130149726945015,"year":144328607719150468}],"nearbyInfoCount":[{"count":8618130149726945015,"year":144328607719150468},{"count":8618130149726945015,"year":144328607719150468},{"count":8618130149726945015,"year":144328607719150468}],"onceInfoCount":[{"count":8618130149726945015,"year":144328607719150468},{"count":8618130149726945015,"year":144328607719150468},{"count":8618130149726945015,"year":144328607719150468}],"onlineInfoCount":[{"count":8618130149726945015,"year":144328607719150468},{"count":8618130149726945015,"year":144328607719150468},{"count":8618130149726945015,"year":144328607719150468},{"count":8618130149726945015,"year":144328607719150468}]}}}},"400":{"description":"","content":{"application/vnd.goa.error":{"schema":{"$ref":"#/components/schemas/Error"},"example":{"fault":false,"id":"123abc","message":"parameter 'p' must be an integer","name":"bad_request","temporary":true,"timeout":false}}}},"500":{"description":"","content":{"application/vnd.goa.error":{"schema":{"$ref":"#/components/schemas/Error"},"example":{"fault":true,"id":"123abc","message":"parameter 'p' must be an integer","name":"bad_request","temporary":true,"timeout":false}}}}}}},"/api/import_file/import_excel_file":{"post":{"tags":["import_file"],"summary":"批量导入","description":"excel数据批量导入，导入数据采用json格式存储","operationId":"import_file#ImportExcelFile","parameters":[{"name":"X-Area","in":"header","description":"区域","allowEmptyValue":true,"required":true,"schema":{"type":"string","description":"区域","example":"abc","minLength":1},"example":"abc"},{"name":"X-Year","in":"header","description":"年份","allowEmptyValue":true,"required":true,"schema":{"type":"integer","description":"年份","example":2020,"format":"int64"},"example":2020},{"name":"X-Type","in":"header","description":"类型","allowEmptyValue":true,"required":true,"schema":{"type":"integer","description":"类型","example":1,"format":"int64"},"example":1}],"requestBody":{"required":true,"content":{"multipart/form-data":{"schema":{"$ref":"#/components/schemas/ImportExcelFileRequestBody"},"example":{"file":"bHpw","filename":"3nb"}}}},"responses":{"200":{"description":"","content":{"application/json":{"schema":{"$ref":"#/components/schemas/SuccessResult"},"example":{"ok":true}}}},"400":{"description":"","content":{"application/vnd.goa.error":{"schema":{"$ref":"#/components/schemas/Error"},"example":{"fault":true,"id":"123abc","message":"parameter 'p' must be an integer","name":"bad_request","temporary":false,"timeout":false}}}},"500":{"description":"","content":{"application/vnd.goa.error":{"schema":{"$ref":"#/components/schemas/Error"},"example":{"fault":false,"id":"123abc","message":"parameter 'p' must be an integer","name":"bad_request","temporary":true,"timeout":true}}}}}}},"/api/import_file/reform_of_administrative":{"post":{"tags":["import_file"],"summary":"行政审批制度改革事项详情","description":"行政审批制度改革事项详情","operationId":"import_file#ReformOfAdministrative","requestBody":{"required":true,"content":{"application/json":{"schema":{"$ref":"#/components/schemas/WaitLineOverviewRequestBody"},"example":{"endDate":"2020-07-27","regionCode":"520100","startDate":"2019-07-27"}}}},"responses":{"200":{"description":"","content":{"application/json":{"schema":{"$ref":"#/components/schemas/ReformOfAdministrativeResponseBody"},"example":{"data":{"pastSplitCount":65,"splitCount":48,"splitRate":32.5},"errcode":0,"errmsg":""}}}},"400":{"description":"","content":{"application/vnd.goa.error":{"schema":{"$ref":"#/components/schemas/Error"},"example":{"fault":false,"id":"123abc","message":"parameter 'p' must be an integer","name":"bad_request","temporary":true,"timeout":false}}}},"500":{"description":"","content":{"application/vnd.goa.error":{"schema":{"$ref":"#/components/schemas/Error"},"example":{"fault":true,"id":"123abc","message":"parameter 'p' must be an integer","name":"bad_request","temporary":true,"timeout":false}}}}}}},"/api/simulation/get_data":{"post":{"tags":["simulation"],"summary":"获取模拟数据","description":"获取模拟数据","operationId":"simulation#GetData","requestBody":{"required":true,"content":{"application/json":{"schema":{"$ref":"#/components/schemas/GetDataRequestBody"},"example":{"key":"对应模块"}}}},"responses":{"200":{"description":"","content":{"application/json":{"schema":{"$ref":"#/components/schemas/GetDataResponseBody"},"example":{"data":{"isShowMock":true,"key":"对应模块","orderBy":1,"orderTimeScope":1,"val":"对应值"},"errcode":0,"errmsg":""}}}},"400":{"description":"","content":{"application/vnd.goa.error":{"schema":{"$ref":"#/components/schemas/Error"},"example":{"fault":false,"id":"123abc","message":"parameter 'p' must be an integer","name":"bad_request","temporary":true,"timeout":true}}}},"500":{"description":"","content":{"application/vnd.goa.error":{"schema":{"$ref":"#/components/schemas/Error"},"example":{"fault":false,"id":"123abc","message":"parameter 'p' must be an integer","name":"bad_request","temporary":true,"timeout":true}}}}},"security":[{"jwt_header_Authorization":["role:user","role:admin","api:read","api:write","api:admin"]}]}},"/api/simulation/set_data":{"post":{"tags":["simulation"],"summary":"设置数据","description":"设置数据","operationId":"simulation#SetData","requestBody":{"required":true,"content":{"application/json":{"schema":{"$ref":"#/components/schemas/SetDataRequestBody"},"example":{"isShowMock":true,"key":"对应模块","orderBy":1,"orderTimeScope":1,"val":"对应值"}}}},"responses":{"200":{"description":"","content":{"application/json":{"schema":{"$ref":"#/components/schemas/SetDataResponseBody"},"example":{"errcode":0,"errmsg":"","result":{"ok":true}}}}},"400":{"description":"","content":{"application/vnd.goa.error":{"schema":{"$ref":"#/components/schemas/Error"},"example":{"fault":false,"id":"123abc","message":"parameter 'p' must be an integer","name":"bad_request","temporary":false,"timeout":true}}}},"500":{"description":"","content":{"application/vnd.goa.error":{"schema":{"$ref":"#/components/schemas/Error"},"example":{"fault":true,"id":"123abc","message":"parameter 'p' must be an integer","name":"bad_request","temporary":true,"timeout":false}}}}},"security":[{"jwt_header_Authorization":["role:user","role:admin","api:read","api:write","api:admin"]}]}},"/api/third_part/get_hall_management_data":{"get":{"tags":["thirdPart"],"summary":"接收大厅管理的数据","description":"接收大厅管理的数据","operationId":"thirdPart#GetActualTimeData","responses":{"200":{"description":"","content":{"application/json":{"schema":{"$ref":"#/components/schemas/GetActualTimeDataResponseBody2"},"example":{"data":[{"cardNum":"1035","name":"小白","ouName":"社保"},{"cardNum":"1035","name":"小白","ouName":"社保"}],"errcode":0,"errmsg":""}}}},"400":{"description":"","content":{"application/vnd.goa.error":{"schema":{"$ref":"#/components/schemas/Error"},"example":{"fault":false,"id":"123abc","message":"parameter 'p' must be an integer","name":"bad_request","temporary":false,"timeout":false}}}},"500":{"description":"","content":{"application/vnd.goa.error":{"schema":{"$ref":"#/components/schemas/Error"},"example":{"fault":false,"id":"123abc","message":"parameter 'p' must be an integer","name":"bad_request","temporary":false,"timeout":true}}}}}}},"/api/third_part/gorm_related_search":{"get":{"tags":["thirdPart"],"summary":"gorm关联查询","description":"gorm关联查询","operationId":"thirdPart#GormRelatedSearch","responses":{"200":{"description":"","content":{"application/json":{"schema":{"$ref":"#/components/schemas/GormRelatedSearchResponseBody"},"example":{"data":[{"companies":[{"industry":1036,"name":"青朵教育","userId":"王大锤"},{"industry":1036,"name":"青朵教育","userId":"王大锤"},{"industry":1036,"name":"青朵教育","userId":"王大锤"}],"id":1035,"name":"小白"},{"companies":[{"industry":1036,"name":"青朵教育","userId":"王大锤"},{"industry":1036,"name":"青朵教育","userId":"王大锤"},{"industry":1036,"name":"青朵教育","userId":"王大锤"}],"id":1035,"name":"小白"}],"errcode":0,"errmsg":""}}}},"400":{"description":"","content":{"application/vnd.goa.error":{"schema":{"$ref":"#/components/schemas/Error"},"example":{"fault":true,"id":"123abc","message":"parameter 'p' must be an integer","name":"bad_request","temporary":true,"timeout":false}}}},"500":{"description":"","content":{"application/vnd.goa.error":{"schema":{"$ref":"#/components/schemas/Error"},"example":{"fault":false,"id":"123abc","message":"parameter 'p' must be an integer","name":"bad_request","temporary":true,"timeout":false}}}}}}},"/api/third_part/receive_third_party_push_data":{"post":{"tags":["thirdPart"],"summary":"接收第三方推送数据","description":"接收第三方推送数据--大厅排队办事实时图基础数据--排号、叫号、办结、评价四阶段","operationId":"thirdPart#ReceiveThirdPartyPushData","requestBody":{"required":true,"content":{"application/json":{"schema":{"$ref":"#/components/schemas/ReceiveThirdPartyPushDataRequestBody"},"example":{"count":21,"data":"","methodName":1}}}},"responses":{"200":{"description":"","content":{"application/json":{"schema":{"$ref":"#/components/schemas/ReceiveThirdPartyPushDataResponseBody"},"example":{"errcode":0,"errmsg":"","result":"getDataSuccess"}}}},"400":{"description":"","content":{"application/vnd.goa.error":{"schema":{"$ref":"#/components/schemas/Error"},"example":{"fault":true,"id":"123abc","message":"parameter 'p' must be an integer","name":"bad_request","temporary":true,"timeout":true}}}},"500":{"description":"","content":{"application/vnd.goa.error":{"schema":{"$ref":"#/components/schemas/Error"},"example":{"fault":false,"id":"123abc","message":"parameter 'p' must be an integer","name":"bad_request","temporary":false,"timeout":false}}}}}}},"/api/user/get_captcha_image":{"post":{"tags":["User"],"summary":"获取图形验证码","description":"获取图形验证码","operationId":"User#GetCaptchaImage","responses":{"200":{"description":"","content":{"application/json":{"schema":{"$ref":"#/components/schemas/GetCaptchaImageResponseBody"},"example":{"data":{"captchaId":"Excepturi et quo.","image":"Ipsam earum aliquam quo voluptate dolor ab."},"errcode":0,"errmsg":""}}}},"400":{"description":"","content":{"application/vnd.goa.error":{"schema":{"$ref":"#/components/schemas/Error"},"example":{"fault":false,"id":"123abc","message":"parameter 'p' must be an integer","name":"bad_request","temporary":true,"timeout":true}}}},"500":{"description":"","content":{"application/vnd.goa.error":{"schema":{"$ref":"#/components/schemas/Error"},"example":{"fault":false,"id":"123abc","message":"parameter 'p' must be an integer","name":"bad_request","temporary":false,"timeout":false}}}}}}},"/api/user/login_by_mobile":{"post":{"tags":["User"],"summary":"使用短信验证码登录","description":"使用短信验证码登录","operationId":"User#LoginBySmsCode","requestBody":{"required":true,"content":{"application/json":{"schema":{"$ref":"#/components/schemas/LoginBySmsCodeRequestBody"},"example":{"mobile":"guest","verify_code":"123456"}}}},"responses":{"200":{"description":"","content":{"application/json":{"schema":{"$ref":"#/components/schemas/LoginByUsernameResponseBody"},"example":{"data":{"cookie":"Nesciunt dolorem.","credentials":{"expires_in":25200,"token":"eyJhbGciOiJIUz..."},"user":{"id":"Molestiae at nihil sed.","isActive":true,"loginTime":"Perspiciatis quasi et optio molestias optio aut.","mobile":"Eos optio ea voluptas voluptatem magnam nostrum.","nickname":"Atque sed occaecati optio.","username":"Consequuntur nostrum."}},"errcode":0,"errmsg":""}}}},"400":{"description":"","content":{"application/vnd.goa.error":{"schema":{"$ref":"#/components/schemas/Error"},"example":{"fault":true,"id":"123abc","message":"parameter 'p' must be an integer","name":"bad_request","temporary":false,"timeout":false}}}},"500":{"description":"","content":{"application/vnd.goa.error":{"schema":{"$ref":"#/components/schemas/Error"},"example":{"fault":true,"id":"123abc","message":"parameter 'p' must be an integer","name":"bad_request","temporary":true,"timeout":false}}}}}}},"/api/user/login_by_username":{"post":{"tags":["User"],"summary":"使用账号密码登录","description":"使用账号密码登录","operationId":"User#LoginByUsername","requestBody":{"required":true,"content":{"application/json":{"schema":{"$ref":"#/components/schemas/LoginByUsernameRequestBody"},"example":{"captchaId":"y","humanCode":"5wj","password":"password","username":"user"}}}},"responses":{"200":{"description":"","content":{"application/json":{"schema":{"$ref":"#/components/schemas/LoginByUsernameResponseBody"},"example":{"data":{"cookie":"Nesciunt dolorem.","credentials":{"expires_in":25200,"token":"eyJhbGciOiJIUz..."},"user":{"id":"Molestiae at nihil sed.","isActive":true,"loginTime":"Perspiciatis quasi et optio molestias optio aut.","mobile":"Eos optio ea voluptas voluptatem magnam nostrum.","nickname":"Atque sed occaecati optio.","username":"Consequuntur nostrum."}},"errcode":0,"errmsg":""}}}},"400":{"description":"","content":{"application/vnd.goa.error":{"schema":{"$ref":"#/components/schemas/Error"},"example":{"fault":true,"id":"123abc","message":"parameter 'p' must be an integer","name":"bad_request","temporary":false,"timeout":false}}}},"500":{"description":"","content":{"application/vnd.goa.error":{"schema":{"$ref":"#/components/schemas/Error"},"example":{"fault":false,"id":"123abc","message":"parameter 'p' must be an integer","name":"bad_request","temporary":false,"timeout":true}}}}}}},"/api/user/send_sms_code":{"post":{"tags":["User"],"summary":"发送短信验证码","description":"发送短信验证码","operationId":"User#SendSmsCode","requestBody":{"required":true,"content":{"application/json":{"schema":{"$ref":"#/components/schemas/SendSmsCodeRequestBody"},"example":{"captchaId":"c","humanCode":"tw4","mobile":"wmi"}}}},"responses":{"200":{"description":"","content":{"application/json":{"schema":{"$ref":"#/components/schemas/UpdatePasswordResponseBody"},"example":{"data":{"ok":true},"errcode":0,"errmsg":""}}}},"400":{"description":"","content":{"application/vnd.goa.error":{"schema":{"$ref":"#/components/schemas/Error"},"example":{"fault":true,"id":"123abc","message":"parameter 'p' must be an integer","name":"bad_request","temporary":false,"timeout":false}}}},"500":{"description":"","content":{"application/vnd.goa.error":{"schema":{"$ref":"#/components/schemas/Error"},"example":{"fault":false,"id":"123abc","message":"parameter 'p' must be an integer","name":"bad_request","temporary":false,"timeout":false}}}}}}},"/api/user/update_password":{"post":{"tags":["User"],"summary":"修改登录密码","description":"修改登录密码","operationId":"User#UpdatePassword","requestBody":{"required":true,"content":{"application/json":{"schema":{"$ref":"#/components/schemas/UpdatePasswordRequestBody"},"example":{"new_password":"abc123","old_password":"123abc"}}}},"responses":{"200":{"description":"","content":{"application/json":{"schema":{"$ref":"#/components/schemas/UpdatePasswordResponseBody"},"example":{"data":{"ok":true},"errcode":0,"errmsg":""}}}},"400":{"description":"","content":{"application/vnd.goa.error":{"schema":{"$ref":"#/components/schemas/Error"},"example":{"fault":false,"id":"123abc","message":"parameter 'p' must be an integer","name":"bad_request","temporary":true,"timeout":true}}}},"500":{"description":"","content":{"application/vnd.goa.error":{"schema":{"$ref":"#/components/schemas/Error"},"example":{"fault":false,"id":"123abc","message":"parameter 'p' must be an integer","name":"bad_request","temporary":true,"timeout":true}}}}},"security":[{"jwt_header_Authorization":["role:user","role:admin","api:read","api:write","api:admin"]}]}}},"components":{"schemas":{"Canaldataresp":{"type":"object","properties":{"dataInfo":{"type":"string","description":"数据","example":1035,"format":"binary"},"dataType":{"type":"integer","description":"数据类别","example":1035,"format":"int32"}},"description":"数据库增量数据","example":{"dataInfo":1035,"dataType":1035},"required":["dataType","dataInfo"]},"Captcha":{"type":"object","properties":{"captchaId":{"type":"string","description":"验证码ID","example":"Porro quo error aut provident dolores sapiente."},"image":{"type":"string","description":"图片base64","example":"Debitis qui aut."}},"example":{"captchaId":"Voluptate et laborum neque.","image":"Saepe adipisci."},"required":["image","captchaId"]},"Companyprofileresp":{"type":"object","properties":{"industry":{"type":"integer","description":"行业Id","example":1036,"format":"int64"},"name":{"type":"string","description":"公司名字","example":"青朵教育"},"userId":{"type":"string","description":"法人名字","example":"王大锤"}},"description":"公司简洁","example":{"industry":1036,"name":"青朵教育","userId":"王大锤"},"required":["industry","name","userId"]},"Credentials":{"type":"object","properties":{"expires_in":{"type":"integer","description":"有效时长（秒）：生成之后x秒内有效","example":25200,"format":"int64"},"token":{"type":"string","description":"JWT token","example":"eyJhbGciOiJIUz..."}},"example":{"expires_in":25200,"token":"eyJhbGciOiJIUz..."},"required":["token","expires_in"]},"CrowdRunsLittleResponseBody":{"type":"object","properties":{"data":{"$ref":"#/components/schemas/Crowdrunslittleresp"},"errcode":{"type":"integer","description":"错误码","example":0,"minimum":0,"maximum":999999},"errmsg":{"type":"string","description":"错误消息","example":""}},"example":{"data":{"mattersAccounted":[{"AfterAscension":120,"beforeAscension":120},{"AfterAscension":120,"beforeAscension":120}],"mattersAccountedProportion":0.8},"errcode":0,"errmsg":""},"required":["errcode","errmsg","data"]},"Crowdrunslittleresp":{"type":"object","properties":{"mattersAccounted":{"type":"array","items":{"$ref":"#/components/schemas/Matternumber"},"description":"总事项不同年份数据","example":[{"AfterAscension":120,"beforeAscension":120},{"AfterAscension":120,"beforeAscension":120},{"AfterAscension":120,"beforeAscension":120}]},"mattersAccountedProportion":{"type":"number","description":"最多跑一次事项占比提升比例","example":0.8,"format":"float"}},"description":"群众少跑腿返回值","example":{"mattersAccounted":[{"AfterAscension":120,"beforeAscension":120},{"AfterAscension":120,"beforeAscension":120},{"AfterAscension":120,"beforeAscension":120},{"AfterAscension":120,"beforeAscension":120}],"mattersAccountedProportion":0.8},"required":["mattersAccounted","mattersAccountedProportion"]},"Error":{"type":"object","properties":{"fault":{"type":"boolean","description":"Is the error a server-side fault?","example":true},"id":{"type":"string","description":"ID is a unique identifier for this particular occurrence of the problem.","example":"123abc"},"message":{"type":"string","description":"Message is a human-readable explanation specific to this occurrence of the problem.","example":"parameter 'p' must be an integer"},"name":{"type":"string","description":"Name is the name of this class of errors.","example":"bad_request"},"temporary":{"type":"boolean","description":"Is the error temporary?","example":false},"timeout":{"type":"boolean","description":"Is the error a timeout?","example":false}},"example":{"fault":false,"id":"123abc","message":"parameter 'p' must be an integer","name":"bad_request","temporary":false,"timeout":true},"required":["name","id","message","temporary","timeout","fault"]},"FourDoCountResp":{"type":"object","properties":{"immediateInfoCount":{"type":"array","items":{"$ref":"#/components/schemas/Fourdo"},"example":[{"count":8618130149726945015,"year":144328607719150468},{"count":8618130149726945015,"year":144328607719150468},{"count":8618130149726945015,"year":144328607719150468},{"count":8618130149726945015,"year":144328607719150468}]},"nearbyInfoCount":{"type":"array","items":{"$ref":"#/components/schemas/Fourdo"},"example":[{"count":8618130149726945015,"year":144328607719150468},{"count":8618130149726945015,"year":144328607719150468},{"count":8618130149726945015,"year":144328607719150468}]},"onceInfoCount":{"type":"array","items":{"$ref":"#/components/schemas/Fourdo"},"example":[{"count":8618130149726945015,"year":144328607719150468},{"count":8618130149726945015,"year":144328607719150468},{"count":8618130149726945015,"year":144328607719150468}]},"onlineInfoCount":{"type":"array","items":{"$ref":"#/components/schemas/Fourdo"},"example":[{"count":8618130149726945015,"year":144328607719150468},{"count":8618130149726945015,"year":144328607719150468}]}},"example":{"immediateInfoCount":[{"count":8618130149726945015,"year":144328607719150468},{"count":8618130149726945015,"year":144328607719150468},{"count":8618130149726945015,"year":144328607719150468},{"count":8618130149726945015,"year":144328607719150468}],"nearbyInfoCount":[{"count":8618130149726945015,"year":144328607719150468},{"count":8618130149726945015,"year":144328607719150468}],"onceInfoCount":[{"count":8618130149726945015,"year":144328607719150468},{"count":8618130149726945015,"year":144328607719150468}],"onlineInfoCount":[{"count":8618130149726945015,"year":144328607719150468},{"count":8618130149726945015,"year":144328607719150468}]},"required":["immediateInfoCount","onlineInfoCount","nearbyInfoCount","onceInfoCount"]},"Fourdo":{"type":"object","properties":{"count":{"type":"integer","description":"数量","example":5835711761455568042,"format":"int64"},"year":{"type":"integer","description":"年份","example":1061867699694468822,"format":"int64"}},"description":"四个办统计","example":{"count":967817043308539909,"year":8894510629519852694},"required":["year","count"]},"GetActualTimeDataResponseBody":{"type":"object","properties":{"data":{"$ref":"#/components/schemas/Canaldataresp"},"errcode":{"type":"integer","description":"错误码","example":0,"minimum":0,"maximum":999999},"errmsg":{"type":"string","description":"错误消息","example":""}},"example":{"data":{"dataInfo":1035,"dataType":1035},"errcode":0,"errmsg":""},"required":["errcode","errmsg","data"]},"GetActualTimeDataResponseBody2":{"type":"object","properties":{"data":{"type":"array","items":{"$ref":"#/components/schemas/Hallmanagementresp"},"example":[{"cardNum":"1035","name":"小白","ouName":"社保"},{"cardNum":"1035","name":"小白","ouName":"社保"},{"cardNum":"1035","name":"小白","ouName":"社保"}]},"errcode":{"type":"integer","description":"错误码","example":0,"minimum":0,"maximum":999999},"errmsg":{"type":"string","description":"错误消息","example":""}},"example":{"data":[{"cardNum":"1035","name":"小白","ouName":"社保"},{"cardNum":"1035","name":"小白","ouName":"社保"},{"cardNum":"1035","name":"小白","ouName":"社保"}],"errcode":0,"errmsg":""},"required":["errcode","errmsg","data"]},"GetCaptchaImageResponseBody":{"type":"object","properties":{"data":{"$ref":"#/components/schemas/Captcha"},"errcode":{"type":"integer","description":"错误码","example":0,"minimum":0,"maximum":999999},"errmsg":{"type":"string","description":"错误消息","example":""}},"example":{"data":{"captchaId":"Excepturi et quo.","image":"Ipsam earum aliquam quo voluptate dolor ab."},"errcode":0,"errmsg":""},"required":["errcode","errmsg"]},"GetDataRequestBody":{"type":"object","properties":{"key":{"type":"string","description":"对应模块","example":"对应模块"}},"example":{"key":"对应模块"},"required":["key"]},"GetDataResponseBody":{"type":"object","properties":{"data":{"$ref":"#/components/schemas/Getdataresp"},"errcode":{"type":"integer","description":"错误码","example":0,"minimum":0,"maximum":999999},"errmsg":{"type":"string","description":"错误消息","example":""}},"example":{"data":{"isShowMock":true,"key":"对应模块","orderBy":1,"orderTimeScope":1,"val":"对应值"},"errcode":0,"errmsg":""},"required":["errcode","errmsg","data"]},"Getdataresp":{"type":"object","properties":{"isShowMock":{"type":"boolean","description":"是否显示配置项","example":true},"key":{"type":"string","description":"对应模块","example":"对应模块"},"orderBy":{"type":"integer","description":"1.通过评分正序 2.通过评分倒序","example":1,"format":"int64"},"orderTimeScope":{"type":"integer","description":"1.按年统计 2.按月统计","example":1,"format":"int64"},"val":{"type":"string","description":"对应值","example":"对应值"}},"description":"获取模拟数据结果","example":{"isShowMock":true,"key":"对应模块","orderBy":1,"orderTimeScope":1,"val":"对应值"},"required":["key","val","isShowMock"]},"GormRelatedSearchResponseBody":{"type":"object","properties":{"data":{"type":"array","items":{"$ref":"#/components/schemas/Legalpersonuserresp"},"example":[{"companies":[{"industry":1036,"name":"青朵教育","userId":"王大锤"},{"industry":1036,"name":"青朵教育","userId":"王大锤"},{"industry":1036,"name":"青朵教育","userId":"王大锤"}],"id":1035,"name":"小白"},{"companies":[{"industry":1036,"name":"青朵教育","userId":"王大锤"},{"industry":1036,"name":"青朵教育","userId":"王大锤"},{"industry":1036,"name":"青朵教育","userId":"王大锤"}],"id":1035,"name":"小白"}]},"errcode":{"type":"integer","description":"错误码","example":0,"minimum":0,"maximum":999999},"errmsg":{"type":"string","description":"错误消息","example":""}},"example":{"data":[{"companies":[{"industry":1036,"name":"青朵教育","userId":"王大锤"},{"industry":1036,"name":"青朵教育","userId":"王大锤"},{"industry":1036,"name":"青朵教育","userId":"王大锤"}],"id":1035,"name":"小白"},{"companies":[{"industry":1036,"name":"青朵教育","userId":"王大锤"},{"industry":1036,"name":"青朵教育","userId":"王大锤"},{"industry":1036,"name":"青朵教育","userId":"王大锤"}],"id":1035,"name":"小白"},{"companies":[{"industry":1036,"name":"青朵教育","userId":"王大锤"},{"industry":1036,"name":"青朵教育","userId":"王大锤"},{"industry":1036,"name":"青朵教育","userId":"王大锤"}],"id":1035,"name":"小白"},{"companies":[{"industry":1036,"name":"青朵教育","userId":"王大锤"},{"industry":1036,"name":"青朵教育","userId":"王大锤"},{"industry":1036,"name":"青朵教育","userId":"王大锤"}],"id":1035,"name":"小白"}],"errcode":0,"errmsg":""},"required":["errcode","errmsg","data"]},"Hallmanagementresp":{"type":"object","properties":{"cardNum":{"type":"string","description":"身份证","example":"1035"},"name":{"type":"string","description":"名字","example":"小白"},"ouName":{"type":"string","description":"部门名字","example":"社保"}},"description":"大厅管理系统数据","example":{"cardNum":"1035","name":"小白","ouName":"社保"},"required":["cardNum","name","ouName"]},"ImportExcelFileRequestBody":{"type":"object","properties":{"file":{"type":"string","description":"上传文件内容","example":"c3pr","maxLength":52428800},"filename":{"type":"string","description":"文件名","example":"tt7","maxLength":128}},"example":{"file":"dnJr","filename":"y57"},"required":["file","filename"]},"Legalpersonuserresp":{"type":"object","properties":{"companies":{"type":"array","items":{"$ref":"#/components/schemas/Companyprofileresp"},"description":"公司","example":[{"industry":1036,"name":"青朵教育","userId":"王大锤"},{"industry":1036,"name":"青朵教育","userId":"王大锤"},{"industry":1036,"name":"青朵教育","userId":"王大锤"}]},"id":{"type":"integer","description":"用户Id","example":1035,"format":"int64"},"name":{"type":"string","description":"名字","example":"小白"}},"description":"法人用户列表","example":{"companies":[{"industry":1036,"name":"青朵教育","userId":"王大锤"},{"industry":1036,"name":"青朵教育","userId":"王大锤"}],"id":1035,"name":"小白"},"required":["id","name","companies"]},"LoginBySmsCodeRequestBody":{"type":"object","properties":{"mobile":{"type":"string","description":"手机号","example":"guest","minLength":11,"maxLength":11},"verify_code":{"type":"string","description":"短信验证码","example":"123456","minLength":4,"maxLength":6}},"example":{"mobile":"guest","verify_code":"123456"},"required":["mobile","verify_code"]},"LoginByUsernameRequestBody":{"type":"object","properties":{"captchaId":{"type":"string","description":"图形验证码ID","default":"","example":"1","minLength":1,"maxLength":128},"humanCode":{"type":"string","description":"图形验证码","default":"","example":"3t0","minLength":4,"maxLength":8},"password":{"type":"string","description":"密码","example":"password","minLength":1,"maxLength":128},"username":{"type":"string","description":"用户名","example":"user","minLength":1,"maxLength":128}},"example":{"captchaId":"fbq","humanCode":"6w9","password":"password","username":"user"},"required":["username","password"]},"LoginByUsernameResponseBody":{"type":"object","properties":{"data":{"$ref":"#/components/schemas/Session"},"errcode":{"type":"integer","description":"错误码","example":0,"minimum":0,"maximum":999999},"errmsg":{"type":"string","description":"错误消息","example":""}},"example":{"data":{"cookie":"Nesciunt dolorem.","credentials":{"expires_in":25200,"token":"eyJhbGciOiJIUz..."},"user":{"id":"Molestiae at nihil sed.","isActive":true,"loginTime":"Perspiciatis quasi et optio molestias optio aut.","mobile":"Eos optio ea voluptas voluptatem magnam nostrum.","nickname":"Atque sed occaecati optio.","username":"Consequuntur nostrum."}},"errcode":0,"errmsg":""},"required":["errcode","errmsg"]},"Matternumber":{"type":"object","properties":{"AfterAscension":{"type":"integer","description":"提升后","example":120,"format":"int32"},"beforeAscension":{"type":"integer","description":"提升前","example":120,"format":"int32"}},"description":"事项数","example":{"AfterAscension":120,"beforeAscension":120},"required":["beforeAscension","AfterAscension"]},"ReceiveThirdPartyPushDataRequestBody":{"type":"object","properties":{"count":{"type":"integer","description":"数据数量","example":21,"format":"int64"},"data":{"type":"string","description":"第三方推送数据","example":"","format":"binary"},"methodName":{"type":"integer","description":"推送的具体方法","example":1,"format":"int64"}},"example":{"count":21,"data":"","methodName":1},"required":["methodName","count","data"]},"ReceiveThirdPartyPushDataResponseBody":{"type":"object","properties":{"errcode":{"type":"integer","description":"错误码","example":0,"minimum":0,"maximum":999999},"errmsg":{"type":"string","description":"错误消息","example":""},"result":{"type":"string","description":"success","example":"getDataSuccess"}},"example":{"errcode":0,"errmsg":"","result":"getDataSuccess"},"required":["errcode","errmsg","result"]},"ReformOfAdministrativeResponseBody":{"type":"object","properties":{"data":{"$ref":"#/components/schemas/Reformofadministrativeresp"},"errcode":{"type":"integer","description":"错误码","example":0,"minimum":0,"maximum":999999},"errmsg":{"type":"string","description":"错误消息","example":""}},"example":{"data":{"pastSplitCount":65,"splitCount":48,"splitRate":32.5},"errcode":0,"errmsg":""},"required":["errcode","errmsg","data"]},"Reformofadministrativeresp":{"type":"object","properties":{"pastSplitCount":{"type":"integer","description":"去年事项大项拆分","example":65,"format":"int32"},"splitCount":{"type":"integer","description":"今年事项大项拆分","example":48,"format":"int32"},"splitRate":{"type":"number","description":"事项拆分比率","example":32.5,"format":"float"}},"description":"行政审批制度改革事项详情","example":{"pastSplitCount":65,"splitCount":48,"splitRate":32.5},"required":["splitCount","pastSplitCount","splitRate"]},"SendSmsCodeRequestBody":{"type":"object","properties":{"captchaId":{"type":"string","description":"图形验证码ID","example":"7i","minLength":1,"maxLength":128},"humanCode":{"type":"string","description":"图形验证码","example":"0un","minLength":4,"maxLength":8},"mobile":{"type":"string","description":"手机号","example":"r58","minLength":11,"maxLength":11}},"example":{"captchaId":"r7x","humanCode":"v67","mobile":"4u3"},"required":["mobile","humanCode","captchaId"]},"Session":{"type":"object","properties":{"cookie":{"type":"string","example":"Adipisci repellendus quo iusto sit voluptatibus aliquid."},"credentials":{"$ref":"#/components/schemas/Credentials"},"user":{"$ref":"#/components/schemas/User"}},"description":"会话","example":{"cookie":"Et quo dolores facilis rem quia doloribus.","credentials":{"expires_in":25200,"token":"eyJhbGciOiJIUz..."},"user":{"id":"Molestiae at nihil sed.","isActive":true,"loginTime":"Perspiciatis quasi et optio molestias optio aut.","mobile":"Eos optio ea voluptas voluptatem magnam nostrum.","nickname":"Atque sed occaecati optio.","username":"Consequuntur nostrum."}},"required":["user","credentials","cookie"]},"SetDataRequestBody":{"type":"object","properties":{"isShowMock":{"type":"boolean","description":"是否显示配置项","example":true},"key":{"type":"string","description":"对应模块","example":"对应模块"},"orderBy":{"type":"integer","description":"1、按评价分正序;2、按评价分倒序","default":1,"example":1,"format":"int64"},"orderTimeScope":{"type":"integer","description":"1、按当年度评价;2、按上个月评价","default":1,"example":1,"format":"int64"},"val":{"type":"string","description":"对应值","example":"对应值"}},"example":{"isShowMock":true,"key":"对应模块","orderBy":1,"orderTimeScope":1,"val":"对应值"},"required":["key","val","isShowMock"]},"SetDataResponseBody":{"type":"object","properties":{"errcode":{"type":"integer","description":"错误码","example":0,"minimum":0,"maximum":999999},"errmsg":{"type":"string","description":"错误消息","example":""},"result":{"$ref":"#/components/schemas/SuccessResult"}},"example":{"errcode":0,"errmsg":"","result":{"ok":true}},"required":["errcode","errmsg","result"]},"SuccessResult":{"type":"object","properties":{"ok":{"type":"boolean","description":"success","example":true}},"example":{"ok":true},"required":["ok"]},"UpdatePasswordRequestBody":{"type":"object","properties":{"new_password":{"type":"string","example":"abc123","minLength":6,"maxLength":128},"old_password":{"type":"string","example":"123abc","minLength":1,"maxLength":128}},"example":{"new_password":"abc123","old_password":"123abc"},"required":["old_password","new_password"]},"UpdatePasswordResponseBody":{"type":"object","properties":{"data":{"$ref":"#/components/schemas/SuccessResult"},"errcode":{"type":"integer","description":"错误码","example":0,"minimum":0,"maximum":999999},"errmsg":{"type":"string","description":"错误消息","example":""}},"example":{"data":{"ok":true},"errcode":0,"errmsg":""},"required":["errcode","errmsg"]},"User":{"type":"object","properties":{"id":{"type":"string","description":"ID","example":"Doloremque porro."},"isActive":{"type":"boolean","description":"是否可用","example":true},"loginTime":{"type":"string","description":"登陆时间","default":"00:00:00","example":"Occaecati voluptate."},"mobile":{"type":"string","description":"手机号","example":"Sit dolorem occaecati est."},"nickname":{"type":"string","description":"昵称","example":"A minus commodi officiis pariatur sapiente."},"username":{"type":"string","description":"用户名","example":"Aperiam minus ut tempore."}},"description":"用户","example":{"id":"Aut ducimus voluptatem consequatur dolor.","isActive":true,"loginTime":"Laborum architecto laudantium autem eum sit dolores.","mobile":"Cumque et quidem dolorem id veritatis non.","nickname":"Neque quia.","username":"Voluptas dolores vero consequuntur."},"required":["id","username","nickname","mobile","isActive"]},"WaitLineOverviewRequestBody":{"type":"object","properties":{"endDate":{"type":"string","description":"结束时间","example":"2020-07-27"},"regionCode":{"type":"string","description":"行政区划代码","example":"520100"},"startDate":{"type":"string","description":"起始时间","example":"2019-07-27"}},"example":{"endDate":"2020-07-27","regionCode":"520100","startDate":"2019-07-27"},"required":["regionCode"]},"WaitLineOverviewResponseBody":{"type":"object","properties":{"data":{"$ref":"#/components/schemas/Waitlineoverviewresp"},"errcode":{"type":"integer","description":"错误码","example":0,"minimum":0,"maximum":999999},"errmsg":{"type":"string","description":"错误消息","example":""}},"example":{"data":{"cumulativeDQ":89362,"todayDQ":1035},"errcode":0,"errmsg":""},"required":["errcode","errmsg","data"]},"Waitlineoverviewresp":{"type":"object","properties":{"cumulativeDQ":{"type":"integer","description":"累计办件量","example":89362,"format":"int32"},"todayDQ":{"type":"integer","description":"累计排号数","example":1035,"format":"int32"}},"description":"排号总览","example":{"cumulativeDQ":89362,"todayDQ":1035},"required":["todayDQ","cumulativeDQ"]}},"securitySchemes":{"jwt_header_Authorization":{"type":"http","description":"使用 JWT 认证, 需要认证的接口添加 ```Header```: ```Authorization: Bearer {jwtToken}```","scheme":"bearer"}}}}