{"openapi":"3.0.3","info":{"title":"微服务","version":"1.0"},"servers":[{"url":"http://localhost:8000/starter","description":"微服务"}],"paths":{"/api/actual_time/get_actual_time_data":{"get":{"tags":["ActualTime"],"summary":"接收数据库监听得到的数据","description":"接收数据库监听得到的数据","operationId":"ActualTime#GetActualTimeData","responses":{"200":{"description":"","content":{"application/json":{"schema":{"$ref":"#/components/schemas/GetActualTimeDataResponseBody"},"example":{"data":{"dataInfo":1035,"dataType":1035},"errcode":0,"errmsg":""}}}},"400":{"description":"","content":{"application/vnd.goa.error":{"schema":{"$ref":"#/components/schemas/Error"},"example":{"fault":true,"id":"123abc","message":"parameter 'p' must be an integer","name":"bad_request","temporary":true,"timeout":false}}}},"500":{"description":"","content":{"application/vnd.goa.error":{"schema":{"$ref":"#/components/schemas/Error"},"example":{"fault":true,"id":"123abc","message":"parameter 'p' must be an integer","name":"bad_request","temporary":true,"timeout":true}}}}}}},"/api/actual_time/receive_third_party_push_data":{"post":{"tags":["ActualTime"],"summary":"接收第三方推送数据","description":"接收第三方推送数据--大厅排队办事实时图基础数据","operationId":"ActualTime#ReceiveThirdPartyPushData","requestBody":{"required":true,"content":{"application/json":{"schema":{"$ref":"#/components/schemas/ReceiveThirdPartyPushDataRequestBody"},"example":{"count":21,"data":"","methodName":1}}}},"responses":{"200":{"description":"","content":{"application/json":{"schema":{"$ref":"#/components/schemas/ReceiveThirdPartyPushDataResponseBody"},"example":{"errcode":0,"errmsg":"","result":"getDataSuccess"}}}},"400":{"description":"","content":{"application/vnd.goa.error":{"schema":{"$ref":"#/components/schemas/Error"},"example":{"fault":true,"id":"123abc","message":"parameter 'p' must be an integer","name":"bad_request","temporary":false,"timeout":true}}}},"500":{"description":"","content":{"application/vnd.goa.error":{"schema":{"$ref":"#/components/schemas/Error"},"example":{"fault":true,"id":"123abc","message":"parameter 'p' must be an integer","name":"bad_request","temporary":true,"timeout":false}}}}}}},"/api/entity_hall/get_wait_line_overview":{"post":{"tags":["entity_hall"],"summary":"排号总览","description":"排号总览","operationId":"entity_hall#WaitLineOverview","requestBody":{"required":true,"content":{"application/json":{"schema":{"$ref":"#/components/schemas/WaitLineOverviewRequestBody"},"example":{"endDate":"2020-07-27","regionCode":"520100","startDate":"2019-07-27"}}}},"responses":{"200":{"description":"","content":{"application/json":{"schema":{"$ref":"#/components/schemas/WaitLineOverviewResponseBody"},"example":{"data":{"cumulativeDQ":89362,"todayDQ":1035},"errcode":0,"errmsg":""}}}},"400":{"description":"","content":{"application/vnd.goa.error":{"schema":{"$ref":"#/components/schemas/Error"},"example":{"fault":false,"id":"123abc","message":"parameter 'p' must be an integer","name":"bad_request","temporary":false,"timeout":false}}}},"500":{"description":"","content":{"application/vnd.goa.error":{"schema":{"$ref":"#/components/schemas/Error"},"example":{"fault":true,"id":"123abc","message":"parameter 'p' must be an integer","name":"bad_request","temporary":false,"timeout":true}}}}}}},"/api/third_part/get_hall_management_data":{"get":{"tags":["thirdPart"],"summary":"接收大厅管理的数据","description":"接收大厅管理的数据","operationId":"thirdPart#GetActualTimeData","responses":{"200":{"description":"","content":{"application/json":{"schema":{"$ref":"#/components/schemas/GetActualTimeDataResponseBody2"},"example":{"data":[{"cardNum":"1035","name":"小白","ouName":"社保"},{"cardNum":"1035","name":"小白","ouName":"社保"}],"errcode":0,"errmsg":""}}}},"400":{"description":"","content":{"application/vnd.goa.error":{"schema":{"$ref":"#/components/schemas/Error"},"example":{"fault":true,"id":"123abc","message":"parameter 'p' must be an integer","name":"bad_request","temporary":true,"timeout":false}}}},"500":{"description":"","content":{"application/vnd.goa.error":{"schema":{"$ref":"#/components/schemas/Error"},"example":{"fault":true,"id":"123abc","message":"parameter 'p' must be an integer","name":"bad_request","temporary":true,"timeout":true}}}}}}},"/api/third_part/gorm_related_search":{"get":{"tags":["thirdPart"],"summary":"gorm关联查询","description":"gorm关联查询","operationId":"thirdPart#GormRelatedSearch","responses":{"200":{"description":"","content":{"application/json":{"schema":{"$ref":"#/components/schemas/GormRelatedSearchResponseBody"},"example":{"data":[{"companies":[{"industry":1036,"name":"青朵教育","userId":"王大锤"},{"industry":1036,"name":"青朵教育","userId":"王大锤"},{"industry":1036,"name":"青朵教育","userId":"王大锤"}],"id":1035,"name":"小白"},{"companies":[{"industry":1036,"name":"青朵教育","userId":"王大锤"},{"industry":1036,"name":"青朵教育","userId":"王大锤"},{"industry":1036,"name":"青朵教育","userId":"王大锤"}],"id":1035,"name":"小白"},{"companies":[{"industry":1036,"name":"青朵教育","userId":"王大锤"},{"industry":1036,"name":"青朵教育","userId":"王大锤"},{"industry":1036,"name":"青朵教育","userId":"王大锤"}],"id":1035,"name":"小白"},{"companies":[{"industry":1036,"name":"青朵教育","userId":"王大锤"},{"industry":1036,"name":"青朵教育","userId":"王大锤"},{"industry":1036,"name":"青朵教育","userId":"王大锤"}],"id":1035,"name":"小白"}],"errcode":0,"errmsg":""}}}},"400":{"description":"","content":{"application/vnd.goa.error":{"schema":{"$ref":"#/components/schemas/Error"},"example":{"fault":true,"id":"123abc","message":"parameter 'p' must be an integer","name":"bad_request","temporary":false,"timeout":true}}}},"500":{"description":"","content":{"application/vnd.goa.error":{"schema":{"$ref":"#/components/schemas/Error"},"example":{"fault":false,"id":"123abc","message":"parameter 'p' must be an integer","name":"bad_request","temporary":false,"timeout":true}}}}}}},"/api/user/get_captcha_image":{"post":{"tags":["User"],"summary":"获取图形验证码","description":"获取图形验证码","operationId":"User#GetCaptchaImage","responses":{"200":{"description":"","content":{"application/json":{"schema":{"$ref":"#/components/schemas/GetCaptchaImageResponseBody"},"example":{"data":{"captchaId":"Debitis velit inventore.","image":"Facilis architecto voluptatem magni magni odit sit."},"errcode":0,"errmsg":""}}}},"400":{"description":"","content":{"application/vnd.goa.error":{"schema":{"$ref":"#/components/schemas/Error"},"example":{"fault":true,"id":"123abc","message":"parameter 'p' must be an integer","name":"bad_request","temporary":false,"timeout":true}}}},"500":{"description":"","content":{"application/vnd.goa.error":{"schema":{"$ref":"#/components/schemas/Error"},"example":{"fault":false,"id":"123abc","message":"parameter 'p' must be an integer","name":"bad_request","temporary":false,"timeout":true}}}}}}},"/api/user/login_by_mobile":{"post":{"tags":["User"],"summary":"使用短信验证码登录","description":"使用短信验证码登录","operationId":"User#LoginBySmsCode","requestBody":{"required":true,"content":{"application/json":{"schema":{"$ref":"#/components/schemas/LoginBySmsCodeRequestBody"},"example":{"mobile":"guest","verify_code":"123456"}}}},"responses":{"200":{"description":"","content":{"application/json":{"schema":{"$ref":"#/components/schemas/LoginByUsernameResponseBody"},"example":{"data":{"cookie":"Eos optio ea voluptas voluptatem magnam nostrum.","credentials":{"expires_in":25200,"token":"eyJhbGciOiJIUz..."},"user":{"id":"Ipsam magni quia minus officiis.","isActive":true,"loginTime":"Atque sed occaecati optio.","mobile":"Nihil sed eaque consequuntur.","nickname":"Quasi molestiae.","username":"Eum et repellat itaque itaque delectus."}},"errcode":0,"errmsg":""}}}},"400":{"description":"","content":{"application/vnd.goa.error":{"schema":{"$ref":"#/components/schemas/Error"},"example":{"fault":true,"id":"123abc","message":"parameter 'p' must be an integer","name":"bad_request","temporary":false,"timeout":true}}}},"500":{"description":"","content":{"application/vnd.goa.error":{"schema":{"$ref":"#/components/schemas/Error"},"example":{"fault":true,"id":"123abc","message":"parameter 'p' must be an integer","name":"bad_request","temporary":false,"timeout":true}}}}}}},"/api/user/login_by_username":{"post":{"tags":["User"],"summary":"使用账号密码登录","description":"使用账号密码登录","operationId":"User#LoginByUsername","requestBody":{"required":true,"content":{"application/json":{"schema":{"$ref":"#/components/schemas/LoginByUsernameRequestBody"},"example":{"captchaId":"zs","humanCode":"rhb","password":"password","username":"user"}}}},"responses":{"200":{"description":"","content":{"application/json":{"schema":{"$ref":"#/components/schemas/LoginByUsernameResponseBody"},"example":{"data":{"cookie":"Eos optio ea voluptas voluptatem magnam nostrum.","credentials":{"expires_in":25200,"token":"eyJhbGciOiJIUz..."},"user":{"id":"Ipsam magni quia minus officiis.","isActive":true,"loginTime":"Atque sed occaecati optio.","mobile":"Nihil sed eaque consequuntur.","nickname":"Quasi molestiae.","username":"Eum et repellat itaque itaque delectus."}},"errcode":0,"errmsg":""}}}},"400":{"description":"","content":{"application/vnd.goa.error":{"schema":{"$ref":"#/components/schemas/Error"},"example":{"fault":false,"id":"123abc","message":"parameter 'p' must be an integer","name":"bad_request","temporary":true,"timeout":false}}}},"500":{"description":"","content":{"application/vnd.goa.error":{"schema":{"$ref":"#/components/schemas/Error"},"example":{"fault":true,"id":"123abc","message":"parameter 'p' must be an integer","name":"bad_request","temporary":false,"timeout":true}}}}}}},"/api/user/send_sms_code":{"post":{"tags":["User"],"summary":"发送短信验证码","description":"发送短信验证码","operationId":"User#SendSmsCode","requestBody":{"required":true,"content":{"application/json":{"schema":{"$ref":"#/components/schemas/SendSmsCodeRequestBody"},"example":{"captchaId":"urr","humanCode":"tmh","mobile":"jve"}}}},"responses":{"200":{"description":"","content":{"application/json":{"schema":{"$ref":"#/components/schemas/UpdatePasswordResponseBody"},"example":{"data":{"ok":true},"errcode":0,"errmsg":""}}}},"400":{"description":"","content":{"application/vnd.goa.error":{"schema":{"$ref":"#/components/schemas/Error"},"example":{"fault":true,"id":"123abc","message":"parameter 'p' must be an integer","name":"bad_request","temporary":true,"timeout":true}}}},"500":{"description":"","content":{"application/vnd.goa.error":{"schema":{"$ref":"#/components/schemas/Error"},"example":{"fault":true,"id":"123abc","message":"parameter 'p' must be an integer","name":"bad_request","temporary":true,"timeout":false}}}}}}},"/api/user/update_password":{"post":{"tags":["User"],"summary":"修改登录密码","description":"修改登录密码","operationId":"User#UpdatePassword","requestBody":{"required":true,"content":{"application/json":{"schema":{"$ref":"#/components/schemas/UpdatePasswordRequestBody"},"example":{"new_password":"abc123","old_password":"123abc"}}}},"responses":{"200":{"description":"","content":{"application/json":{"schema":{"$ref":"#/components/schemas/UpdatePasswordResponseBody"},"example":{"data":{"ok":true},"errcode":0,"errmsg":""}}}},"400":{"description":"","content":{"application/vnd.goa.error":{"schema":{"$ref":"#/components/schemas/Error"},"example":{"fault":false,"id":"123abc","message":"parameter 'p' must be an integer","name":"bad_request","temporary":false,"timeout":false}}}},"500":{"description":"","content":{"application/vnd.goa.error":{"schema":{"$ref":"#/components/schemas/Error"},"example":{"fault":false,"id":"123abc","message":"parameter 'p' must be an integer","name":"bad_request","temporary":false,"timeout":false}}}}},"security":[{"jwt_header_Authorization":["role:user","role:admin"]}]}}},"components":{"schemas":{"Canaldataresp":{"type":"object","properties":{"dataInfo":{"type":"string","description":"数据","example":1035,"format":"binary"},"dataType":{"type":"integer","description":"数据类别","example":1035,"format":"int32"}},"description":"数据库增量数据","example":{"dataInfo":1035,"dataType":1035},"required":["dataType","dataInfo"]},"Captcha":{"type":"object","properties":{"captchaId":{"type":"string","description":"验证码ID","example":"Saepe nisi qui reiciendis et quisquam."},"image":{"type":"string","description":"图片base64","example":"Est et ut veniam corporis et."}},"example":{"captchaId":"Nihil quae saepe et facilis.","image":"Et quaerat et est doloribus repudiandae."},"required":["image","captchaId"]},"Companyprofileresp":{"type":"object","properties":{"industry":{"type":"integer","description":"行业Id","example":1036,"format":"int64"},"name":{"type":"string","description":"公司名字","example":"青朵教育"},"userId":{"type":"string","description":"法人名字","example":"王大锤"}},"description":"公司简洁","example":{"industry":1036,"name":"青朵教育","userId":"王大锤"},"required":["industry","name","userId"]},"Credentials":{"type":"object","properties":{"expires_in":{"type":"integer","description":"有效时长（秒）：生成之后x秒内有效","example":25200,"format":"int64"},"token":{"type":"string","description":"JWT token","example":"eyJhbGciOiJIUz..."}},"example":{"expires_in":25200,"token":"eyJhbGciOiJIUz..."},"required":["token","expires_in"]},"Error":{"type":"object","properties":{"fault":{"type":"boolean","description":"Is the error a server-side fault?","example":false},"id":{"type":"string","description":"ID is a unique identifier for this particular occurrence of the problem.","example":"123abc"},"message":{"type":"string","description":"Message is a human-readable explanation specific to this occurrence of the problem.","example":"parameter 'p' must be an integer"},"name":{"type":"string","description":"Name is the name of this class of errors.","example":"bad_request"},"temporary":{"type":"boolean","description":"Is the error temporary?","example":false},"timeout":{"type":"boolean","description":"Is the error a timeout?","example":false}},"example":{"fault":true,"id":"123abc","message":"parameter 'p' must be an integer","name":"bad_request","temporary":true,"timeout":true},"required":["name","id","message","temporary","timeout","fault"]},"GetActualTimeDataResponseBody":{"type":"object","properties":{"data":{"$ref":"#/components/schemas/Canaldataresp"},"errcode":{"type":"integer","description":"错误码","example":0,"minimum":0,"maximum":999999},"errmsg":{"type":"string","description":"错误消息","example":""}},"example":{"data":{"dataInfo":1035,"dataType":1035},"errcode":0,"errmsg":""},"required":["errcode","errmsg","data"]},"GetActualTimeDataResponseBody2":{"type":"object","properties":{"data":{"type":"array","items":{"$ref":"#/components/schemas/Hallmanagementresp"},"example":[{"cardNum":"1035","name":"小白","ouName":"社保"},{"cardNum":"1035","name":"小白","ouName":"社保"}]},"errcode":{"type":"integer","description":"错误码","example":0,"minimum":0,"maximum":999999},"errmsg":{"type":"string","description":"错误消息","example":""}},"example":{"data":[{"cardNum":"1035","name":"小白","ouName":"社保"},{"cardNum":"1035","name":"小白","ouName":"社保"},{"cardNum":"1035","name":"小白","ouName":"社保"},{"cardNum":"1035","name":"小白","ouName":"社保"}],"errcode":0,"errmsg":""},"required":["errcode","errmsg","data"]},"GetCaptchaImageResponseBody":{"type":"object","properties":{"data":{"$ref":"#/components/schemas/Captcha"},"errcode":{"type":"integer","description":"错误码","example":0,"minimum":0,"maximum":999999},"errmsg":{"type":"string","description":"错误消息","example":""}},"example":{"data":{"captchaId":"Debitis velit inventore.","image":"Facilis architecto voluptatem magni magni odit sit."},"errcode":0,"errmsg":""},"required":["errcode","errmsg"]},"GormRelatedSearchResponseBody":{"type":"object","properties":{"data":{"type":"array","items":{"$ref":"#/components/schemas/Legalpersonuserresp"},"example":[{"companies":[{"industry":1036,"name":"青朵教育","userId":"王大锤"},{"industry":1036,"name":"青朵教育","userId":"王大锤"},{"industry":1036,"name":"青朵教育","userId":"王大锤"}],"id":1035,"name":"小白"},{"companies":[{"industry":1036,"name":"青朵教育","userId":"王大锤"},{"industry":1036,"name":"青朵教育","userId":"王大锤"},{"industry":1036,"name":"青朵教育","userId":"王大锤"}],"id":1035,"name":"小白"},{"companies":[{"industry":1036,"name":"青朵教育","userId":"王大锤"},{"industry":1036,"name":"青朵教育","userId":"王大锤"},{"industry":1036,"name":"青朵教育","userId":"王大锤"}],"id":1035,"name":"小白"},{"companies":[{"industry":1036,"name":"青朵教育","userId":"王大锤"},{"industry":1036,"name":"青朵教育","userId":"王大锤"},{"industry":1036,"name":"青朵教育","userId":"王大锤"}],"id":1035,"name":"小白"}]},"errcode":{"type":"integer","description":"错误码","example":0,"minimum":0,"maximum":999999},"errmsg":{"type":"string","description":"错误消息","example":""}},"example":{"data":[{"companies":[{"industry":1036,"name":"青朵教育","userId":"王大锤"},{"industry":1036,"name":"青朵教育","userId":"王大锤"},{"industry":1036,"name":"青朵教育","userId":"王大锤"}],"id":1035,"name":"小白"},{"companies":[{"industry":1036,"name":"青朵教育","userId":"王大锤"},{"industry":1036,"name":"青朵教育","userId":"王大锤"},{"industry":1036,"name":"青朵教育","userId":"王大锤"}],"id":1035,"name":"小白"},{"companies":[{"industry":1036,"name":"青朵教育","userId":"王大锤"},{"industry":1036,"name":"青朵教育","userId":"王大锤"},{"industry":1036,"name":"青朵教育","userId":"王大锤"}],"id":1035,"name":"小白"},{"companies":[{"industry":1036,"name":"青朵教育","userId":"王大锤"},{"industry":1036,"name":"青朵教育","userId":"王大锤"},{"industry":1036,"name":"青朵教育","userId":"王大锤"}],"id":1035,"name":"小白"}],"errcode":0,"errmsg":""},"required":["errcode","errmsg","data"]},"Hallmanagementresp":{"type":"object","properties":{"cardNum":{"type":"string","description":"身份证","example":"1035"},"name":{"type":"string","description":"名字","example":"小白"},"ouName":{"type":"string","description":"部门名字","example":"社保"}},"description":"大厅管理系统数据","example":{"cardNum":"1035","name":"小白","ouName":"社保"},"required":["cardNum","name","ouName"]},"Legalpersonuserresp":{"type":"object","properties":{"companies":{"type":"array","items":{"$ref":"#/components/schemas/Companyprofileresp"},"description":"公司","example":[{"industry":1036,"name":"青朵教育","userId":"王大锤"},{"industry":1036,"name":"青朵教育","userId":"王大锤"},{"industry":1036,"name":"青朵教育","userId":"王大锤"},{"industry":1036,"name":"青朵教育","userId":"王大锤"}]},"id":{"type":"integer","description":"用户Id","example":1035,"format":"int64"},"name":{"type":"string","description":"名字","example":"小白"}},"description":"法人用户列表","example":{"companies":[{"industry":1036,"name":"青朵教育","userId":"王大锤"},{"industry":1036,"name":"青朵教育","userId":"王大锤"}],"id":1035,"name":"小白"},"required":["id","name","companies"]},"LoginBySmsCodeRequestBody":{"type":"object","properties":{"mobile":{"type":"string","description":"手机号","example":"guest","minLength":11,"maxLength":11},"verify_code":{"type":"string","description":"短信验证码","example":"123456","minLength":4,"maxLength":6}},"example":{"mobile":"guest","verify_code":"123456"},"required":["mobile","verify_code"]},"LoginByUsernameRequestBody":{"type":"object","properties":{"captchaId":{"type":"string","description":"图形验证码ID","default":"","example":"4e","minLength":1,"maxLength":128},"humanCode":{"type":"string","description":"图形验证码","default":"","example":"w8i","minLength":4,"maxLength":8},"password":{"type":"string","description":"密码","example":"password","minLength":1,"maxLength":128},"username":{"type":"string","description":"用户名","example":"user","minLength":1,"maxLength":128}},"example":{"captchaId":"z1","humanCode":"kiv","password":"password","username":"user"},"required":["username","password"]},"LoginByUsernameResponseBody":{"type":"object","properties":{"data":{"$ref":"#/components/schemas/Session"},"errcode":{"type":"integer","description":"错误码","example":0,"minimum":0,"maximum":999999},"errmsg":{"type":"string","description":"错误消息","example":""}},"example":{"data":{"cookie":"Eos optio ea voluptas voluptatem magnam nostrum.","credentials":{"expires_in":25200,"token":"eyJhbGciOiJIUz..."},"user":{"id":"Ipsam magni quia minus officiis.","isActive":true,"loginTime":"Atque sed occaecati optio.","mobile":"Nihil sed eaque consequuntur.","nickname":"Quasi molestiae.","username":"Eum et repellat itaque itaque delectus."}},"errcode":0,"errmsg":""},"required":["errcode","errmsg"]},"ReceiveThirdPartyPushDataRequestBody":{"type":"object","properties":{"count":{"type":"integer","description":"数据数量","example":21,"format":"int64"},"data":{"type":"string","description":"第三方推送数据","example":"","format":"binary"},"methodName":{"type":"integer","description":"推送的具体方法","example":1,"format":"int64"}},"example":{"count":21,"data":"","methodName":1},"required":["methodName","count","data"]},"ReceiveThirdPartyPushDataResponseBody":{"type":"object","properties":{"errcode":{"type":"integer","description":"错误码","example":0,"minimum":0,"maximum":999999},"errmsg":{"type":"string","description":"错误消息","example":""},"result":{"type":"string","description":"success","example":"getDataSuccess"}},"example":{"errcode":0,"errmsg":"","result":"getDataSuccess"},"required":["errcode","errmsg","result"]},"SendSmsCodeRequestBody":{"type":"object","properties":{"captchaId":{"type":"string","description":"图形验证码ID","example":"0","minLength":1,"maxLength":128},"humanCode":{"type":"string","description":"图形验证码","example":"2y6","minLength":4,"maxLength":8},"mobile":{"type":"string","description":"手机号","example":"ebk","minLength":11,"maxLength":11}},"example":{"captchaId":"u4k","humanCode":"xq7","mobile":"k7o"},"required":["mobile","humanCode","captchaId"]},"Session":{"type":"object","properties":{"cookie":{"type":"string","example":"Optio sit unde eum est."},"credentials":{"$ref":"#/components/schemas/Credentials"},"user":{"$ref":"#/components/schemas/User"}},"description":"会话","example":{"cookie":"Ut nesciunt voluptatibus.","credentials":{"expires_in":25200,"token":"eyJhbGciOiJIUz..."},"user":{"id":"Ipsam magni quia minus officiis.","isActive":true,"loginTime":"Atque sed occaecati optio.","mobile":"Nihil sed eaque consequuntur.","nickname":"Quasi molestiae.","username":"Eum et repellat itaque itaque delectus."}},"required":["user","credentials","cookie"]},"Successresult":{"type":"object","properties":{"ok":{"type":"boolean","description":"success","example":true}},"description":"成功信息","example":{"ok":true},"required":["ok"]},"UpdatePasswordRequestBody":{"type":"object","properties":{"new_password":{"type":"string","example":"abc123","minLength":6,"maxLength":128},"old_password":{"type":"string","example":"123abc","minLength":1,"maxLength":128}},"example":{"new_password":"abc123","old_password":"123abc"},"required":["old_password","new_password"]},"UpdatePasswordResponseBody":{"type":"object","properties":{"data":{"$ref":"#/components/schemas/Successresult"},"errcode":{"type":"integer","description":"错误码","example":0,"minimum":0,"maximum":999999},"errmsg":{"type":"string","description":"错误消息","example":""}},"example":{"data":{"ok":true},"errcode":0,"errmsg":""},"required":["errcode","errmsg"]},"User":{"type":"object","properties":{"id":{"type":"string","description":"ID","example":"Quae voluptatem facere vel ratione velit."},"isActive":{"type":"boolean","description":"是否可用","example":true},"loginTime":{"type":"string","description":"登陆时间","default":"00:00:00","example":"Consequatur est."},"mobile":{"type":"string","description":"手机号","example":"Eos qui eum ipsa."},"nickname":{"type":"string","description":"昵称","example":"Voluptas est repellat ab."},"username":{"type":"string","description":"用户名","example":"Rerum voluptatem saepe et id fuga."}},"description":"用户","example":{"id":"Quibusdam quae.","isActive":false,"loginTime":"Fuga eum.","mobile":"Officia alias ducimus dolorem.","nickname":"Consequatur nihil tempora.","username":"Voluptatem et voluptas perspiciatis excepturi nesciunt ipsam."},"required":["id","username","nickname","mobile","isActive"]},"WaitLineOverviewRequestBody":{"type":"object","properties":{"endDate":{"type":"string","description":"结束时间","example":"2020-07-27"},"regionCode":{"type":"string","description":"行政区划代码","example":"520100"},"startDate":{"type":"string","description":"起始时间","example":"2019-07-27"}},"example":{"endDate":"2020-07-27","regionCode":"520100","startDate":"2019-07-27"},"required":["regionCode"]},"WaitLineOverviewResponseBody":{"type":"object","properties":{"data":{"$ref":"#/components/schemas/Waitlineoverviewresp"},"errcode":{"type":"integer","description":"错误码","example":0,"minimum":0,"maximum":999999},"errmsg":{"type":"string","description":"错误消息","example":""}},"example":{"data":{"cumulativeDQ":89362,"todayDQ":1035},"errcode":0,"errmsg":""},"required":["errcode","errmsg","data"]},"Waitlineoverviewresp":{"type":"object","properties":{"cumulativeDQ":{"type":"integer","description":"累计办件量","example":89362,"format":"int32"},"todayDQ":{"type":"integer","description":"累计排号数","example":1035,"format":"int32"}},"description":"排号总览","example":{"cumulativeDQ":89362,"todayDQ":1035},"required":["todayDQ","cumulativeDQ"]}},"securitySchemes":{"jwt_header_Authorization":{"type":"http","description":"JWT 认证","scheme":"bearer"}}}}